pipt/__init__.py
pipt/cli/main.py
pipt/core/errors.py
pipt/core/index.py
pipt/core/options.py
pipt/core/resolver.py
pipt/core/timeutil.py
pipt-0.1.7.dist-info/licenses/LICENSE
pipt-0.1.7.dist-info/METADATA
pipt-0.1.7.dist-info/WHEEL
pipt-0.1.7.dist-info/entry_points.txt
pipt-0.1.7.dist-info/top_level.txt
pipt-0.1.7.dist-info/RECORD
