Metadata-Version: 2.4
Name: pipt
Version: 0.1.7
Summary: A time machine for your Python environment. Install packages as they existed on a given date.
Author: pipt contributors
License: MIT
Project-URL: Homepage, https://github.com/OsamaS99/pipt
Project-URL: Repository, https://github.com/OsamaS99/pipt
Project-URL: Issues, https://github.com/OsamaS99/pipt/issues
Keywords: pip,reproducibility,dependencies,packages,PyPI,time travel
Classifier: Programming Language :: Python :: 3
Classifier: Programming Language :: Python :: 3 :: Only
Classifier: License :: OSI Approved :: MIT License
Classifier: Operating System :: OS Independent
Classifier: Environment :: Console
Classifier: Intended Audience :: Developers
Classifier: Topic :: Software Development :: Build Tools
Requires-Python: >=3.9
License-File: LICENSE
Requires-Dist: httpx>=0.27
Requires-Dist: packaging>=24.1
Requires-Dist: rich>=13.7
Requires-Dist: diskcache>=5.6
Requires-Dist: typer>=0.12
Provides-Extra: dev
Requires-Dist: pytest>=8; extra == "dev"
Requires-Dist: pytest-vcr>=1.0; extra == "dev"
Requires-Dist: pytest-mock>=3.12; extra == "dev"
Requires-Dist: ruff>=0.5; extra == "dev"
Requires-Dist: mypy>=1.10; extra == "dev"
Dynamic: license-file
